lfg3/__init__.py
lfg3/utils.py
lfg3-0.0.4.dist-info/LICENSE
lfg3-0.0.4.dist-info/METADATA
lfg3-0.0.4.dist-info/WHEEL
lfg3-0.0.4.dist-info/RECORD
