Metadata-Version: 2.1
Name: lfg3
Version: 0.0.4
Summary: ether
Home-page: https://github.com/monokh/lfg3
Author: monokh
Requires-Python: >=3.8,<4.0
Classifier: Programming Language :: Python :: 3
Classifier: Programming Language :: Python :: 3.8
Classifier: Programming Language :: Python :: 3.9
Classifier: Programming Language :: Python :: 3.10
Classifier: Programming Language :: Python :: 3.11
Project-URL: Repository, https://github.com/monokh/lfg3
